statai/__init__.py
statai-0.0.0.dist-info/METADATA
statai-0.0.0.dist-info/WHEEL
statai-0.0.0.dist-info/top_level.txt
statai-0.0.0.dist-info/RECORD
